{
  "source_gate_report": "experiments/results/lidar_degeneracy/policy_gate/policy_gate_report.json",
  "policy": {
    "path": "evaluation/config/lidar_degeneracy_triage_policy.json",
    "policy_version": "lidar_degeneracy_triage_v1",
    "strict_gate": {
      "max_fail_rows": 0,
      "max_investigate_rows": 0,
      "require_policy_version_match": true
    }
  },
  "summary": {
    "action_items": 4,
    "offender_rows": 14,
    "category_rows": {
      "cross_method_disagreement": 6,
      "false_confidence_risk": 4,
      "local_matcher_failure": 4
    },
    "method_rows": {
      "geometry_icp": 4,
      "intensity_bev": 8,
      "kiss_keyframe": 2
    }
  },
  "action_items": [
    {
      "priority": 1,
      "policy_decision": "fail",
      "category": "local_matcher_failure",
      "method": "geometry_icp",
      "title": "Repair local matcher acceptance and convergence",
      "component": "local registration",
      "recommended_action": "Inspect per-pair registration decisions, overlap, and acceptance gates; add fallback or retry behavior before relaxing the strict gate.",
      "offender_rows": 4,
      "reports": {
        "method_health_comparison": 2,
        "risk_gt_calibration": 2
      },
      "reasons": {
        "low_acceptance": 4,
        "all_pairs_failed": 2
      },
      "windows": [
        {
          "sequence": "fog_200",
          "window": "point_count_tail",
          "start": 115,
          "end": 144,
          "rows": 2
        },
        {
          "sequence": "fog_200",
          "window": "degraded",
          "start": 170,
          "end": 199,
          "rows": 2
        }
      ],
      "evidence": [
        {
          "report": "method_health_comparison",
          "sequence": "fog_200",
          "window": "degraded",
          "start": 170,
          "end": 199,
          "method": "geometry_icp",
          "policy_decision": "fail",
          "policy_reasons": [
            "all_pairs_failed",
            "low_acceptance"
          ]
        },
        {
          "report": "method_health_comparison",
          "sequence": "fog_200",
          "window": "point_count_tail",
          "start": 115,
          "end": 144,
          "method": "geometry_icp",
          "policy_decision": "fail",
          "policy_reasons": [
            "low_acceptance"
          ]
        },
        {
          "report": "risk_gt_calibration",
          "sequence": "fog_200",
          "window": "degraded",
          "start": 170,
          "end": 199,
          "method": "geometry_icp",
          "policy_decision": "fail",
          "policy_reasons": [
            "all_pairs_failed",
            "low_acceptance"
          ]
        },
        {
          "report": "risk_gt_calibration",
          "sequence": "fog_200",
          "window": "point_count_tail",
          "start": 115,
          "end": 144,
          "method": "geometry_icp",
          "policy_decision": "fail",
          "policy_reasons": [
            "low_acceptance"
          ]
        }
      ]
    },
    {
      "priority": 2,
      "policy_decision": "investigate",
      "category": "false_confidence_risk",
      "method": "intensity_bev",
      "title": "Calibrate false-confidence health signals",
      "component": "failure awareness",
      "recommended_action": "Tighten motion-margin and overlap-tail checks so confident-looking trajectories are downgraded when degeneracy evidence is strong.",
      "offender_rows": 4,
      "reports": {
        "method_health_comparison": 2,
        "risk_gt_calibration": 2
      },
      "reasons": {
        "motion_margin_dominant": 4,
        "overlap_tail": 2
      },
      "windows": [
        {
          "sequence": "fog_200",
          "window": "point_count_tail",
          "start": 115,
          "end": 144,
          "rows": 2
        },
        {
          "sequence": "tunnel_geom_2700_200",
          "window": "degraded",
          "start": 170,
          "end": 199,
          "rows": 2
        }
      ],
      "evidence": [
        {
          "report": "method_health_comparison",
          "sequence": "fog_200",
          "window": "point_count_tail",
          "start": 115,
          "end": 144,
          "method": "intensity_bev",
          "policy_decision": "investigate",
          "policy_reasons": [
            "motion_margin_dominant",
            "overlap_tail"
          ]
        },
        {
          "report": "method_health_comparison",
          "sequence": "tunnel_geom_2700_200",
          "window": "degraded",
          "start": 170,
          "end": 199,
          "method": "intensity_bev",
          "policy_decision": "investigate",
          "policy_reasons": [
            "motion_margin_dominant"
          ]
        },
        {
          "report": "risk_gt_calibration",
          "sequence": "fog_200",
          "window": "point_count_tail",
          "start": 115,
          "end": 144,
          "method": "intensity_bev",
          "policy_decision": "investigate",
          "policy_reasons": [
            "motion_margin_dominant",
            "overlap_tail"
          ]
        },
        {
          "report": "risk_gt_calibration",
          "sequence": "tunnel_geom_2700_200",
          "window": "degraded",
          "start": 170,
          "end": 199,
          "method": "intensity_bev",
          "policy_decision": "investigate",
          "policy_reasons": [
            "motion_margin_dominant"
          ]
        }
      ]
    },
    {
      "priority": 3,
      "policy_decision": "investigate",
      "category": "cross_method_disagreement",
      "method": "intensity_bev",
      "title": "Investigate cross-method trajectory disagreement",
      "component": "cross-method validation",
      "recommended_action": "Compare the suspect method against healthy peers, inspect path-length ratios, and require a second signal before accepting the pose stream.",
      "offender_rows": 4,
      "reports": {
        "method_health_comparison": 2,
        "risk_gt_calibration": 2
      },
      "reasons": {
        "cross_method_suspicious": 4,
        "path_disagrees_with_healthy_median": 4,
        "path_disagrees_with_all_method_median": 2
      },
      "windows": [
        {
          "sequence": "tunnel_geom_2700_200",
          "window": "point_count_tail",
          "start": 80,
          "end": 109,
          "rows": 2
        },
        {
          "sequence": "tunnel_geom_2700_200",
          "window": "geometry_degeneracy",
          "start": 90,
          "end": 119,
          "rows": 2
        }
      ],
      "evidence": [
        {
          "report": "method_health_comparison",
          "sequence": "tunnel_geom_2700_200",
          "window": "geometry_degeneracy",
          "start": 90,
          "end": 119,
          "method": "intensity_bev",
          "policy_decision": "investigate",
          "policy_reasons": [
            "cross_method_suspicious",
            "path_disagrees_with_all_method_median",
            "path_disagrees_with_healthy_median"
          ]
        },
        {
          "report": "method_health_comparison",
          "sequence": "tunnel_geom_2700_200",
          "window": "point_count_tail",
          "start": 80,
          "end": 109,
          "method": "intensity_bev",
          "policy_decision": "investigate",
          "policy_reasons": [
            "cross_method_suspicious",
            "path_disagrees_with_healthy_median"
          ]
        },
        {
          "report": "risk_gt_calibration",
          "sequence": "tunnel_geom_2700_200",
          "window": "geometry_degeneracy",
          "start": 90,
          "end": 119,
          "method": "intensity_bev",
          "policy_decision": "investigate",
          "policy_reasons": [
            "cross_method_suspicious",
            "path_disagrees_with_all_method_median",
            "path_disagrees_with_healthy_median"
          ]
        },
        {
          "report": "risk_gt_calibration",
          "sequence": "tunnel_geom_2700_200",
          "window": "point_count_tail",
          "start": 80,
          "end": 109,
          "method": "intensity_bev",
          "policy_decision": "investigate",
          "policy_reasons": [
            "cross_method_suspicious",
            "path_disagrees_with_healthy_median"
          ]
        }
      ]
    },
    {
      "priority": 4,
      "policy_decision": "investigate",
      "category": "cross_method_disagreement",
      "method": "kiss_keyframe",
      "title": "Investigate cross-method trajectory disagreement",
      "component": "cross-method validation",
      "recommended_action": "Compare the suspect method against healthy peers, inspect path-length ratios, and require a second signal before accepting the pose stream.",
      "offender_rows": 2,
      "reports": {
        "method_health_comparison": 1,
        "risk_gt_calibration": 1
      },
      "reasons": {
        "cross_method_suspicious": 2,
        "path_disagrees_with_healthy_median": 2
      },
      "windows": [
        {
          "sequence": "fog_200",
          "window": "degraded",
          "start": 170,
          "end": 199,
          "rows": 2
        }
      ],
      "evidence": [
        {
          "report": "method_health_comparison",
          "sequence": "fog_200",
          "window": "degraded",
          "start": 170,
          "end": 199,
          "method": "kiss_keyframe",
          "policy_decision": "investigate",
          "policy_reasons": [
            "cross_method_suspicious",
            "path_disagrees_with_healthy_median"
          ]
        },
        {
          "report": "risk_gt_calibration",
          "sequence": "fog_200",
          "window": "degraded",
          "start": 170,
          "end": 199,
          "method": "kiss_keyframe",
          "policy_decision": "investigate",
          "policy_reasons": [
            "cross_method_suspicious",
            "path_disagrees_with_healthy_median"
          ]
        }
      ]
    }
  ]
}
