{
  "schema_version": 1,
  "problem": {
    "id": "kiss_icp_profile_tradeoff_hdl_400_reference_b",
    "title": "KISS-ICP throughput and drift trade-off on the second public HDL-400 reference window",
    "question": "Which KISS-ICP odometry profile should stay as the current default on a deeper HDL-400 public reference set while keeping faster and denser alternatives comparable?",
    "dataset": {
      "pcd_dir": "dogfooding_results/hdl_400_open_ct_lio_120_b",
      "gt_csv": "experiments/reference_data/hdl_400_public_reference_b.csv",
      "reference_role": "public reference trajectory sliced from the HDL-400 pose trace export"
    },
    "same_metrics": [
      "ate_m",
      "fps",
      "readability_score",
      "extensibility_score"
    ]
  },
  "stable_interface": {
    "binary": "build/evaluation/pcd_dogfooding",
    "methods": "kiss_icp",
    "primary_method": "KISS-ICP"
  },
  "variants": [
    {
      "id": "balanced_local_map",
      "label": "Balanced local map",
      "design_style": "balanced",
      "intent": "Keep the current repository default as the odometry baseline.",
      "args": []
    },
    {
      "id": "fast_recent_map",
      "label": "Fast recent map",
      "design_style": "throughput-oriented",
      "intent": "Reduce source density and map pressure to improve FPS.",
      "args": [
        "--kiss-fast-profile"
      ]
    },
    {
      "id": "dense_local_map",
      "label": "Dense local map",
      "design_style": "drift-oriented",
      "intent": "Increase source density and local-map richness to fight odometry drift.",
      "args": [
        "--kiss-dense-profile"
      ]
    }
  ]
}
